markdown2pdf/__init__.py
markdown2pdf/client.py
markdown2pdf/exceptions.py
markdown2pdf/types.py
markdown2pdf_python-0.2.0.dist-info/licenses/LICENSE
markdown2pdf_python-0.2.0.dist-info/METADATA
markdown2pdf_python-0.2.0.dist-info/WHEEL
markdown2pdf_python-0.2.0.dist-info/top_level.txt
markdown2pdf_python-0.2.0.dist-info/RECORD
