Metadata-Version: 2.4
Name: markdown2pdf-python
Version: 0.2.0
Summary: ⚡ Python client for markdown2pdf.ai - Convert markdown to PDF with Lightning payments
Author: Serendipity AI
License: MIT
Project-URL: Homepage, https://markdown2pdf.ai
Project-URL: Documentation, https://markdown2pdf.ai
Project-URL: Repository, https://github.com/Serendipity-AI/markdown2pdf-python
Requires-Python: >=3.7
License-File: LICENSE
Requires-Dist: dotenv>=0.9.9
Requires-Dist: httpx>=0.24.1
Requires-Dist: requests
Dynamic: license-file
